README.rst
setup.py
itchecker/__init__.py
itchecker/access.py
itchecker/base_checker.py
itchecker/console_tool.py
itchecker/excel.py
itchecker/requirements.txt
itchecker/word.py
itchecker/word_test.py
itchecker.egg-info/PKG-INFO
itchecker.egg-info/SOURCES.txt
itchecker.egg-info/dependency_links.txt
itchecker.egg-info/entry_points.txt
itchecker.egg-info/requires.txt
itchecker.egg-info/top_level.txt
itchecker/templates/access_report.html
itchecker/templates/excel_report.html
itchecker/templates/word_report.html