Metadata-Version: 2.1
Name: itchecker
Version: 2.0
Summary: Python command line application bare bones template.
Home-page: UNKNOWN
Author: itolymp
Author-email: it@itolymp.com
License: UNKNOWN
Platform: UNKNOWN
